ArcticCloud/BaseConverter.py
ArcticCloud/MarkSheet.py
ArcticCloud/__init__.py
ArcticCloud-1.0.1.dist-info/LICENSE.txt
ArcticCloud-1.0.1.dist-info/METADATA
ArcticCloud-1.0.1.dist-info/WHEEL
ArcticCloud-1.0.1.dist-info/top_level.txt
ArcticCloud-1.0.1.dist-info/RECORD
