Metadata-Version: 2.1
Name: ArcticCloud
Version: 1.0.1
Summary: A Library containing modules for Daily tasks
Home-page: https://github.com/Stark-Corp/ArcticCloud/
Author: Apurba Ghosh
Author-email: new.to.world2003@gmail.com
License: UNKNOWN
Platform: UNKNOWN
Classifier: Programming Language :: Python :: 3
Classifier: License :: OSI Approved :: MIT License
Classifier: Operating System :: OS Independent
Requires-Python: >= 3.6
